spellchecker/__init__.py
spellchecker/spellchecker.py
yamlspellchecker-0.1.9.dist-info/METADATA
yamlspellchecker-0.1.9.dist-info/WHEEL
yamlspellchecker-0.1.9.dist-info/entry_points.txt
yamlspellchecker-0.1.9.dist-info/top_level.txt
yamlspellchecker-0.1.9.dist-info/RECORD
