Metadata-Version: 2.1
Name: yamlspellchecker
Version: 0.1.9
Summary: Spell checker for YAML files
Home-page: UNKNOWN
Author: kodSIM
Author-email: UNKNOWN
License: UNKNOWN
Platform: UNKNOWN
Requires-Dist: Click
Requires-Dist: nltk
